CHANGES.txt
LICENSE.txt
MANIFEST.in
README.md
ez_setup.py
setup.py
DemoPackage/__init__.py
DemoPackage/utils.py
DemoPackage.egg-info/PKG-INFO
DemoPackage.egg-info/SOURCES.txt
DemoPackage.egg-info/dependency_links.txt
DemoPackage.egg-info/namespace_packages.txt
DemoPackage.egg-info/requires.txt
DemoPackage.egg-info/top_level.txt
DemoPackage/tests/__init__.py
DemoPackage/tests/test_utils.py
bin/sample.py
docs/.gitignore
docs/DemoPackage.rst
docs/DemoPackage.tests.rst
docs/Makefile
docs/conf.py
docs/index.rst
docs/make.bat
docs/_build/doctrees/DemoPackage.doctree
docs/_build/doctrees/DemoPackage.tests.doctree
docs/_build/doctrees/environment.pickle
docs/_build/doctrees/index.doctree
docs/_build/html/.buildinfo
docs/_build/html/.nojekyll
docs/_build/html/DemoPackage.html
docs/_build/html/DemoPackage.tests.html
docs/_build/html/genindex.html
docs/_build/html/index.html
docs/_build/html/objects.inv
docs/_build/html/py-modindex.html
docs/_build/html/search.html
docs/_build/html/searchindex.js
docs/_build/html/.git/COMMIT_EDITMSG
docs/_build/html/.git/HEAD
docs/_build/html/.git/config
docs/_build/html/.git/description
docs/_build/html/.git/index
docs/_build/html/.git/packed-refs
docs/_build/html/.git/hooks/applypatch-msg.sample
docs/_build/html/.git/hooks/commit-msg.sample
docs/_build/html/.git/hooks/post-update.sample
docs/_build/html/.git/hooks/pre-applypatch.sample
docs/_build/html/.git/hooks/pre-commit.sample
docs/_build/html/.git/hooks/pre-rebase.sample
docs/_build/html/.git/hooks/prepare-commit-msg.sample
docs/_build/html/.git/hooks/update.sample
docs/_build/html/.git/info/exclude
docs/_build/html/.git/logs/HEAD
docs/_build/html/.git/logs/refs/heads/gh-pages
docs/_build/html/.git/logs/refs/heads/master
docs/_build/html/.git/logs/refs/remotes/origin/gh-pages
docs/_build/html/.git/objects/3a/94aa676b20d73a3ca2261d4023043d0bd3daf5
docs/_build/html/.git/objects/56/b0538157ec60bf18dd06169b1faeb765101fab
docs/_build/html/.git/objects/5f/d565d54d227209be6cc08b2429716618d4b0f6
docs/_build/html/.git/objects/6b/242a9989d966d32fb077d4ccd083efc7c279ee
docs/_build/html/.git/objects/73/e85ec3036b542c7eecad928a027c9b6867d6c4
docs/_build/html/.git/objects/76/b0b82a7d91194062ac426f8a66d0215eb62177
