Metadata-Version: 1.1
Name: DemoPackage
Version: 0.0.1
Summary: QuantSoftware Toolkit
Home-page: http://sb2nov.github.io/DemoPackage
Author: Sourabh Bajaj
Author-email: sourabhbajaj90@gmail.com
License: Copyright (c) <2013>, <Sourabh Bajaj>
